d2m/__init__.py
d2m/checker.py
d2m-0.0.18.dist-info/LICENSE
d2m-0.0.18.dist-info/METADATA
d2m-0.0.18.dist-info/WHEEL
d2m-0.0.18.dist-info/top_level.txt
d2m-0.0.18.dist-info/RECORD
