Metadata-Version: 2.1
Name: d2m
Version: 0.0.18
Summary: A dataframe health checker.
Home-page: https://github.com/bonzoyang/d2m/
Author: Bonzo Yang
Author-email: bonzoyang@gmail.com
License: UNKNOWN
Platform: UNKNOWN
Classifier: Programming Language :: Python :: 3
Classifier: License :: OSI Approved :: MIT License
Classifier: Operating System :: OS Independent
Requires-Python: >=3.8
